AUTHORS
LICENSE
MANIFEST.in
changelog.rst
run-tests.py
setup.py
SimpleURL.egg-info/PKG-INFO
SimpleURL.egg-info/SOURCES.txt
SimpleURL.egg-info/dependency_links.txt
SimpleURL.egg-info/not-zip-safe
SimpleURL.egg-info/requires.txt
SimpleURL.egg-info/top_level.txt
simpleurl/__init__.py
tests/__init__.py
tests/client.py
tests/server.py