Metadata-Version: 1.1
Name: SimpleURL
Version: 0.0.6
Summary: Werkzeug based routing system for Brubeck - Escape from Regex
Home-page: https://github.com/kracekumar/simpleurl
Author: kracekumar
Author-email: me@kracekumar.com
License: Lesser General Public License (LGPL)
Platform: any
Classifier: Development Status :: 2 - Pre-Alpha
Classifier: Environment :: Web Environment
Classifier: Intended Audience :: Developers
Classifier: License :: OSI Approved :: GNU Lesser General Public License v3 or later (LGPLv3+)
Classifier: Operating System :: OS Independent
Classifier: Programming Language :: Python
Classifier: Topic :: Internet :: WWW/HTTP :: Dynamic Content
Classifier: Topic :: Software Development :: Libraries :: Python Modules
